rc/__init__.py
rc/__main__.py
rc/_build.py
rc/_debug.py
rc/_rc_version.py
rc/analytics.py
rc/api.py
rc/api_client.py
rc/build.py
rc/config.py
rc/dirs.py
rc/dvc.py
rc/env.py
rc/error_messages.py
rc/exceptions.py
rc/git.py
rc/info.py
rc/logger.py
rc/profile.py
rc/progress.py
rc/prompt.py
rc/required_config_keys.py
rc/version.py
rc/cli/__init__.py
rc/cli/command.py
rc/cli/parser.py
rc/cli/utils.py
rc/commands/__init__.py
rc/commands/config.py
rc/commands/get.py
rc/commands/put.py
rc/commands/repo.py
rc/entities/__init__.py
rc/entities/repos.py
rc/repo/__init__.py
rc/repo/clone.py
rc/repo/create.py
rc/repo/get.py
rc/repo/put.py
rc/ui/__init__.py
rc/utils/__init__.py
rc/utils/run_cli_cmd.py
raga_cli-0.1.76.dist-info/LICENSE
raga_cli-0.1.76.dist-info/METADATA
raga_cli-0.1.76.dist-info/WHEEL
raga_cli-0.1.76.dist-info/entry_points.txt
raga_cli-0.1.76.dist-info/top_level.txt
raga_cli-0.1.76.dist-info/RECORD
